{
  "cards": [
    {
      "id": 1,
      "description": "Go on a date with a mime artist"
    },
    {
      "id": 2,
      "description": "Sing everything you say out loud"
    },
    {
      "id": 3,
      "description": "Never be able to open your mouth"
    },
    {
      "id": 4,
      "description": "Be in an outdoors jacuzzi in -40 weather"
    }
  ]
}
Sit in first class on a long-haul flight next to the smelliest person on the planet, Live rent free in a flat next to Māngere Wastewater Treatment Plant, Go on a date with Dua Lipa, Spend a weekend in NYC, Be married to the world's wealthiest octogenarian with no prenuptial agreement, Be a fly on Kanye's bedroom wall, Be the Cambridge's live-in child-minder, Be flipped by Graham Norton, Get 9 weeks of training by Jaqen H'ghar
